{
  "updatedAt": "2026-07-12T15:00:58.399Z",
  "live": [
    {
      "memberKey": "partner:従井ノラ",
      "name": "従井ノラ",
      "groupId": "partner",
      "groupName": "パートナークリエイター",
      "groupColor": "#f5db6e",
      "channelId": "UCQYy35PowPpc6ImRH1TQgcw",
      "handle": "nora_shitagai",
      "videoId": "BHqG4wNSOlc",
      "title": "【初見SEKIRO/隻狼】迷えば漏れる、おしがまSEKIRO最終回【従井ノラ】",
      "thumbnail": "https://i.ytimg.com/vi/BHqG4wNSOlc/mqdefault_live.jpg",
      "scheduledStart": "2026-07-12T06:00:00Z",
      "url": "https://www.youtube.com/watch?v=BHqG4wNSOlc",
      "checkedAt": "2026-07-12T15:00:58.383Z",
      "status": "live"
    },
    {
      "memberKey": "goraku:回胴てん",
      "name": "回胴てん",
      "groupId": "goraku",
      "groupName": "娯楽組",
      "groupColor": "#c49bff",
      "channelId": "UCcuJiXr5imCUjFCHhFm1WmA",
      "handle": "回胴てん",
      "videoId": "QxCzQuZnao0",
      "title": "【ASMR】とろとろマッサージで耳溶けちゃう♡【娯楽/回胴てん】",
      "thumbnail": "https://i.ytimg.com/vi/QxCzQuZnao0/mqdefault_live.jpg",
      "scheduledStart": "2026-07-12T14:00:52Z",
      "url": "https://www.youtube.com/watch?v=QxCzQuZnao0",
      "checkedAt": "2026-07-12T15:00:58.383Z",
      "status": "live"
    }
  ],
  "upcoming": [
    {
      "memberKey": "aogiri:音霊魂子",
      "name": "音霊魂子",
      "groupId": "aogiri",
      "groupName": "あおぎり高校",
      "groupColor": "#7db8ff",
      "channelId": "UCt7_srJeiw55kTcK7M9ID6g",
      "handle": "tamako0212",
      "videoId": "BsTVRsoF1o8",
      "title": "【オフコラボ】お家でたこ焼きパーティーをして仲を深めたいですッ！！【#あおぎり高校 #ホロライブ 】",
      "thumbnail": "https://i.ytimg.com/vi/BsTVRsoF1o8/mqdefault_live.jpg",
      "scheduledStart": "2026-07-13T09:30:00Z",
      "url": "https://www.youtube.com/watch?v=BsTVRsoF1o8",
      "checkedAt": "2026-07-12T15:00:58.383Z",
      "status": "upcoming"
    },
    {
      "memberKey": "bebop:数寄屋橋れんげ",
      "name": "数寄屋橋れんげ",
      "groupId": "bebop",
      "groupName": "ビバップ高校",
      "groupColor": "#6ee7aa",
      "channelId": "UCBxgYX7hJy6TZVvLXOEQrWw",
      "handle": "renge_morinyan",
      "videoId": "gpdghYPQCZY",
      "title": "【バロン👻イベスト】トリッカルで学ぶコンプライアンス！【 #数寄屋橋れんげ / VTuber 】",
      "thumbnail": "https://i.ytimg.com/vi/gpdghYPQCZY/mqdefault_live.jpg",
      "scheduledStart": "2026-07-15T09:00:00Z",
      "url": "https://www.youtube.com/watch?v=gpdghYPQCZY",
      "checkedAt": "2026-07-10T08:25:25.138Z",
      "status": "upcoming"
    },
    {
      "memberKey": "yugiri:運命メイナ",
      "name": "運命メイナ",
      "groupId": "yugiri",
      "groupName": "ゆうぎり高校",
      "groupColor": "#ffb070",
      "channelId": "UCbsgSnDh12vTloogn0g6lPQ",
      "handle": "DestinyMeina",
      "videoId": "soothCp5Ibc",
      "title": "【ゆうモニ】最後の朝活やり切れるのか...！【運命メイナ/ゆうぎり高校】",
      "thumbnail": "https://i.ytimg.com/vi/soothCp5Ibc/mqdefault_live.jpg",
      "scheduledStart": "2026-07-15T22:00:00Z",
      "url": "https://www.youtube.com/watch?v=soothCp5Ibc",
      "checkedAt": "2026-07-12T15:00:58.383Z",
      "status": "upcoming"
    },
    {
      "memberKey": "yugiri:運命メイナ",
      "name": "運命メイナ",
      "groupId": "yugiri",
      "groupName": "ゆうぎり高校",
      "groupColor": "#ffb070",
      "channelId": "UCbsgSnDh12vTloogn0g6lPQ",
      "handle": "DestinyMeina",
      "videoId": "x5sezrcIH8U",
      "title": "【コラボ】デビューから１ヶ月！？【運命メイナ/ゆうぎり高校】",
      "thumbnail": "https://i.ytimg.com/vi/x5sezrcIH8U/mqdefault_live.jpg",
      "scheduledStart": "2026-07-18T11:00:00Z",
      "url": "https://www.youtube.com/watch?v=x5sezrcIH8U",
      "checkedAt": "2026-07-12T15:00:58.383Z",
      "status": "upcoming"
    }
  ]
}
