{
  "updatedAt": "2026-07-12T08:00:54.982Z",
  "live": [
    {
      "memberKey": "aogiri:うる虎がーる",
      "name": "うる虎がーる",
      "groupId": "aogiri",
      "groupName": "あおぎり高校",
      "groupColor": "#7db8ff",
      "channelId": "UCdi5pj0MDQ-3LFNUFIFmD8w",
      "handle": "urutoragaru0831",
      "videoId": "3IMojda2In8",
      "title": "【 FF9 】 完全初見でファイナルファンタジーⅨをプレイ！＃６【 うる虎がーる / FINAL FANTASY Ⅸ 】",
      "thumbnail": "https://i.ytimg.com/vi/3IMojda2In8/mqdefault_live.jpg",
      "scheduledStart": "2026-07-12T06:00:00Z",
      "url": "https://www.youtube.com/watch?v=3IMojda2In8",
      "checkedAt": "2026-07-12T08:00:54.943Z",
      "status": "live"
    },
    {
      "memberKey": "partner:従井ノラ",
      "name": "従井ノラ",
      "groupId": "partner",
      "groupName": "パートナークリエイター",
      "groupColor": "#f5db6e",
      "channelId": "UCQYy35PowPpc6ImRH1TQgcw",
      "handle": "nora_shitagai",
      "videoId": "BHqG4wNSOlc",
      "title": "【初見SEKIRO/隻狼】迷えば漏れる、おしがまSEKIRO最終回【従井ノラ】",
      "thumbnail": "https://i.ytimg.com/vi/BHqG4wNSOlc/mqdefault_live.jpg",
      "scheduledStart": "2026-07-12T06:00:00Z",
      "url": "https://www.youtube.com/watch?v=BHqG4wNSOlc",
      "checkedAt": "2026-07-12T08:00:54.943Z",
      "status": "live"
    },
    {
      "memberKey": "yugiri:LN_へるぷ.exe",
      "name": "LN_へるぷ.exe",
      "groupId": "yugiri",
      "groupName": "ゆうぎり高校",
      "groupColor": "#ffb070",
      "channelId": "UCzvizEAhqHm0D1fEa-hNiLg",
      "handle": "LN_Help_exe",
      "videoId": "0PcXmfnNZ40",
      "title": "【BIOHAZARD requiem】わけもわからず巻き込まれたグレース、療養所から逃げ出せるの⁉",
      "thumbnail": "https://i.ytimg.com/vi/0PcXmfnNZ40/mqdefault_live.jpg",
      "scheduledStart": "2026-07-12T06:00:00Z",
      "url": "https://www.youtube.com/watch?v=0PcXmfnNZ40",
      "checkedAt": "2026-07-12T08:00:54.943Z",
      "status": "live"
    }
  ],
  "upcoming": [
    {
      "memberKey": "bebop:泡喰はわこ",
      "name": "泡喰はわこ",
      "groupId": "bebop",
      "groupName": "ビバップ高校",
      "groupColor": "#6ee7aa",
      "channelId": "UCQjIXLk6lridUCQIBHaLMDw",
      "handle": "hawako_meiwaku",
      "videoId": "Z5eyHNdN2-M",
      "title": "零 ～紅い蝶～ REMAKE 🎮ホラー夏の挑戦3日目 ※ネタバレ注意【泡喰はわこ/ビバップ高校 /迷電ワークス  】",
      "thumbnail": "https://i.ytimg.com/vi/Z5eyHNdN2-M/mqdefault_live.jpg",
      "scheduledStart": "2026-07-12T08:30:00Z",
      "url": "https://www.youtube.com/watch?v=Z5eyHNdN2-M",
      "checkedAt": "2026-07-12T08:00:54.943Z",
      "status": "upcoming"
    },
    {
      "memberKey": "bebop:数寄屋橋れんげ",
      "name": "数寄屋橋れんげ",
      "groupId": "bebop",
      "groupName": "ビバップ高校",
      "groupColor": "#6ee7aa",
      "channelId": "UCBxgYX7hJy6TZVvLXOEQrWw",
      "handle": "renge_morinyan",
      "videoId": "OUMACR-IETQ",
      "title": "【初見ロックマンエグゼ6】コピーロイドとかいうヤバすぎる発明は早く一般家庭に普及してください【電脳獣グレイガ】 #数寄屋橋れんげ / VTuber",
      "thumbnail": "https://i.ytimg.com/vi/OUMACR-IETQ/mqdefault_live.jpg",
      "scheduledStart": "2026-07-12T09:00:00Z",
      "url": "https://www.youtube.com/watch?v=OUMACR-IETQ",
      "checkedAt": "2026-07-12T08:00:54.943Z",
      "status": "upcoming"
    },
    {
      "memberKey": "aogiri:石狩あかり",
      "name": "石狩あかり",
      "groupId": "aogiri",
      "groupName": "あおぎり高校",
      "groupColor": "#7db8ff",
      "channelId": "UC7wZb5INldbGweowOhBIs8Q",
      "handle": "akari0415",
      "videoId": "rk4tKRUFldo",
      "title": "【】【】",
      "thumbnail": "https://i.ytimg.com/vi/rk4tKRUFldo/mqdefault.jpg",
      "scheduledStart": "2026-07-12T10:00:00Z",
      "url": "https://www.youtube.com/watch?v=rk4tKRUFldo",
      "checkedAt": "2026-07-12T08:00:54.943Z",
      "status": "upcoming"
    },
    {
      "memberKey": "bebop:甘葛すもあ",
      "name": "甘葛すもあ",
      "groupId": "bebop",
      "groupName": "ビバップ高校",
      "groupColor": "#6ee7aa",
      "channelId": "UCAflRAT6B_7nvxAK72ztN3A",
      "handle": "sumoa_meiwaku",
      "videoId": "gM1V1py92qg",
      "title": "【高評価500目指せ】🎤歌枠🎶手ぶらで参る！腰の痛みがＭＡＸになったら、立って歌う【甘葛すもあ/ビバップ高校】",
      "thumbnail": "https://i.ytimg.com/vi/gM1V1py92qg/mqdefault_live.jpg",
      "scheduledStart": "2026-07-12T10:00:00Z",
      "url": "https://www.youtube.com/watch?v=gM1V1py92qg",
      "checkedAt": "2026-07-12T08:00:54.943Z",
      "status": "upcoming"
    },
    {
      "memberKey": "aogiri:石狩あかり",
      "name": "石狩あかり",
      "groupId": "aogiri",
      "groupName": "あおぎり高校",
      "groupColor": "#7db8ff",
      "channelId": "UC7wZb5INldbGweowOhBIs8Q",
      "handle": "akari0415",
      "videoId": "O1gHrR0CSDE",
      "title": "【リトルナイトメア3】チャプター3から仲良く遊ぶ！【石狩あかり/月赴ゐぶき】",
      "thumbnail": "https://i.ytimg.com/vi/O1gHrR0CSDE/mqdefault_live.jpg",
      "scheduledStart": "2026-07-12T11:00:00Z",
      "url": "https://www.youtube.com/watch?v=O1gHrR0CSDE",
      "checkedAt": "2026-07-12T08:00:54.943Z",
      "status": "upcoming"
    },
    {
      "memberKey": "aogiri:春雨麗女",
      "name": "春雨麗女",
      "groupId": "aogiri",
      "groupName": "あおぎり高校",
      "groupColor": "#7db8ff",
      "channelId": "UCmiYJycZXBGc4s_zjIRUHhQ",
      "handle": "urame0711",
      "videoId": "eTEMo9bVczU",
      "title": "【超実写 / 閲覧注意】周年だから実写もギターも見せちゃうよん🎸見てからの苦情は受け付けません【#春雨麗女 #あおぎり高校】",
      "thumbnail": "https://i.ytimg.com/vi/eTEMo9bVczU/mqdefault_live.jpg",
      "scheduledStart": "2026-07-12T12:00:00Z",
      "url": "https://www.youtube.com/watch?v=eTEMo9bVczU",
      "checkedAt": "2026-07-12T08:00:54.943Z",
      "status": "upcoming"
    },
    {
      "memberKey": "goraku:落乃いなほ",
      "name": "落乃いなほ",
      "groupId": "goraku",
      "groupName": "娯楽組",
      "groupColor": "#c49bff",
      "channelId": "UCxk-xk9E_GS8Z5qJ-iBYLyw",
      "handle": "落乃いなほ",
      "videoId": "peYU2Pf6VVw",
      "title": "Karena aku sudah punya penerjemah khusus, sekarang aku bisa kolaborasi! 😎✨",
      "thumbnail": "https://i.ytimg.com/vi/peYU2Pf6VVw/mqdefault_live.jpg",
      "scheduledStart": "2026-07-12T12:00:00Z",
      "url": "https://www.youtube.com/watch?v=peYU2Pf6VVw",
      "checkedAt": "2026-07-12T08:00:54.943Z",
      "status": "upcoming"
    },
    {
      "memberKey": "aogiri:音霊魂子",
      "name": "音霊魂子",
      "groupId": "aogiri",
      "groupName": "あおぎり高校",
      "groupColor": "#7db8ff",
      "channelId": "UCt7_srJeiw55kTcK7M9ID6g",
      "handle": "tamako0212",
      "videoId": "BsTVRsoF1o8",
      "title": "【オフコラボ】お家でたこ焼きパーティーをして仲を深めたいですッ！！【#あおぎり高校 #ホロライブ 】",
      "thumbnail": "https://i.ytimg.com/vi/BsTVRsoF1o8/mqdefault_live.jpg",
      "scheduledStart": "2026-07-13T09:30:00Z",
      "url": "https://www.youtube.com/watch?v=BsTVRsoF1o8",
      "checkedAt": "2026-07-12T08:00:54.942Z",
      "status": "upcoming"
    },
    {
      "memberKey": "bebop:数寄屋橋れんげ",
      "name": "数寄屋橋れんげ",
      "groupId": "bebop",
      "groupName": "ビバップ高校",
      "groupColor": "#6ee7aa",
      "channelId": "UCBxgYX7hJy6TZVvLXOEQrWw",
      "handle": "renge_morinyan",
      "videoId": "gpdghYPQCZY",
      "title": "【バロン👻イベスト】トリッカルで学ぶコンプライアンス！【 #数寄屋橋れんげ / VTuber 】",
      "thumbnail": "https://i.ytimg.com/vi/gpdghYPQCZY/mqdefault_live.jpg",
      "scheduledStart": "2026-07-15T09:00:00Z",
      "url": "https://www.youtube.com/watch?v=gpdghYPQCZY",
      "checkedAt": "2026-07-10T08:25:25.138Z",
      "status": "upcoming"
    },
    {
      "memberKey": "yugiri:運命メイナ",
      "name": "運命メイナ",
      "groupId": "yugiri",
      "groupName": "ゆうぎり高校",
      "groupColor": "#ffb070",
      "channelId": "UCbsgSnDh12vTloogn0g6lPQ",
      "handle": "DestinyMeina",
      "videoId": "soothCp5Ibc",
      "title": "【ゆうモニ】最後の朝活やり切れるのか...！【運命メイナ/ゆうぎり高校】",
      "thumbnail": "https://i.ytimg.com/vi/soothCp5Ibc/mqdefault_live.jpg",
      "scheduledStart": "2026-07-15T22:00:00Z",
      "url": "https://www.youtube.com/watch?v=soothCp5Ibc",
      "checkedAt": "2026-07-12T08:00:54.943Z",
      "status": "upcoming"
    },
    {
      "memberKey": "yugiri:運命メイナ",
      "name": "運命メイナ",
      "groupId": "yugiri",
      "groupName": "ゆうぎり高校",
      "groupColor": "#ffb070",
      "channelId": "UCbsgSnDh12vTloogn0g6lPQ",
      "handle": "DestinyMeina",
      "videoId": "x5sezrcIH8U",
      "title": "【コラボ】デビューから１ヶ月！？【運命メイナ/ゆうぎり高校】",
      "thumbnail": "https://i.ytimg.com/vi/x5sezrcIH8U/mqdefault_live.jpg",
      "scheduledStart": "2026-07-18T11:00:00Z",
      "url": "https://www.youtube.com/watch?v=x5sezrcIH8U",
      "checkedAt": "2026-07-12T08:00:54.943Z",
      "status": "upcoming"
    }
  ]
}
